pytime_manager
