Metadata-Version: 2.1
Name: pytime-manager
Version: 1.6.2
Summary: Improves work with time in Python.
Home-page: https://github.com/xzripper/time_manager
Download-URL: https://github.com/xzripper/time_manager/archive/refs/tags/v1.6.2.tar.gz
Author: Ivan Perzhinsky.
Author-email: name1not1found.com@gmail.com
License: MIT
Keywords: utility
Classifier: Development Status :: 5 - Production/Stable 
Classifier: Intended Audience :: Developers
Classifier: Topic :: Utilities
Classifier: License :: OSI Approved :: MIT License
Classifier: Programming Language :: Python :: 3
License-File: LICENSE.txt
